classad2/__init__.py
classad2/_class_ad.py
classad2/_expr_tree.py
classad2/_parser_type.py
classad2/_value.py
classad2/classad2_impl.abi3.so
classad3/ClassAd.py
classad3/Expression.py
classad3/__init__.py
htcondor.libs/libSciTokens-ee37b48c.so.0.0.2
htcondor.libs/libbrotlicommon-6ce2a53c.so.1.0.6
htcondor.libs/libbrotlidec-811d1be3.so.1.0.6
htcondor.libs/libclassad-df8e4936.so.25.6.1
htcondor.libs/libcom_err-730ca923.so.2.1
htcondor.libs/libcondor_utils_25_6_1-e1630411.so
htcondor.libs/libcrypt-52aca757.so.1.1.0
htcondor.libs/libcrypto-bdaed0ea.so.1.1.1k
htcondor.libs/libcurl-14a7698c.so.4.5.0
htcondor.libs/libgomp-e985bcbb.so.1.0.0
htcondor.libs/libgssapi_krb5-323bbd21.so.2.2
htcondor.libs/libidn2-2f4a5893.so.0.3.6
htcondor.libs/libk5crypto-9a74ff38.so.3.1
htcondor.libs/libkeyutils-2777d33d.so.1.6
htcondor.libs/libkrb5-a55300e8.so.3.3
htcondor.libs/libkrb5support-e6594cfc.so.0.1
htcondor.libs/liblber-2-d20824ef.4.so.2.10.9
htcondor.libs/libldap-2-cea2a960.4.so.2.10.9
htcondor.libs/libmunge-76a62566.so.2.0.0
htcondor.libs/libnghttp2-39367a22.so.14.17.0
htcondor.libs/libpcre2-8-516f4c9d.so.0.7.1
htcondor.libs/libpsl-99becdd3.so.5.3.1
htcondor.libs/libsasl2-7de4d792.so.3.0.0
htcondor.libs/libselinux-d0805dcb.so.1
htcondor.libs/libsqlite3-1ec6053f.so.0.8.6
htcondor.libs/libssh-9f6d898c.so.4.8.7
htcondor.libs/libssl-60250281.so.1.1.1k
htcondor.libs/libunistring-05abdd40.so.2.1.0
htcondor.libs/libuuid-e4c4d8e4.so.1.3.0
htcondor2/__init__.py
htcondor2/_ad_type.py
htcondor2/_collector.py
htcondor2/_common_files_event_type.py
htcondor2/_common_imports.py
htcondor2/_completion_type.py
htcondor2/_cred_check.py
htcondor2/_cred_type.py
htcondor2/_credd.py
htcondor2/_daemon_command.py
htcondor2/_daemon_type.py
htcondor2/_dagman.py
htcondor2/_drain_type.py
htcondor2/_file_transfer_event_type.py
htcondor2/_history_src.py
htcondor2/_job_action.py
htcondor2/_job_event.py
htcondor2/_job_event_log.py
htcondor-25.6.1.dist-info/METADATA
htcondor-25.6.1.dist-info/WHEEL
htcondor-25.6.1.dist-info/top_level.txt
htcondor-25.6.1.dist-info/RECORD
htcondor-25.6.1.dist-info/sboms/auditwheel.cdx.json
